scan_image_slicer/__init__.py
scan_image_slicer/__version__.py
scan_image_slicer/config.py
scan_image_slicer/confparser.py
scan_image_slicer/gui.py
scan_image_slicer/gui_widgets.py
scan_image_slicer/scan_image_slicer.py
scan_image_slicer/scis.py
scan_image_slicer/scis_image.py
scan_image_slicer/scis_logger.py
scan_image_slicer/utils.py
scan_image_slicer/imutils/LICENSE.txt
scan_image_slicer/imutils/__init__.py
scan_image_slicer/imutils/perspective.py
scan_image_slicer-2.0.2.dist-info/entry_points.txt
scan_image_slicer-2.0.2.dist-info/LICENSE
scan_image_slicer-2.0.2.dist-info/WHEEL
scan_image_slicer-2.0.2.dist-info/METADATA
scan_image_slicer-2.0.2.dist-info/RECORD
