Metadata-Version: 2.1
Name: scan-image-slicer
Version: 2.0.2
Summary: A tool for detecting and slicing images
Keywords: scanner,scan,slice,slicer,image,photo,digitize
Author-email: hiemb <highonember@gmail.com>
Requires-Python: >=3.10
Classifier: Development Status :: 4 - Beta
Classifier: Operating System :: OS Independent
Classifier: License :: OSI Approved :: GNU General Public License v3 or later (GPLv3+)
Classifier: Environment :: Console
Classifier: Intended Audience :: End Users/Desktop
Classifier: Topic :: Scientific/Engineering :: Image Recognition
Classifier: Topic :: Scientific/Engineering :: Image Processing
Classifier: Topic :: Multimedia :: Graphics :: Capture :: Scanners
Requires-Dist: pillow
Requires-Dist: pillow_lut
Requires-Dist: FreeSimpleGUI
Requires-Dist: numpy
Requires-Dist: opencv-python
Requires-Dist: imutils
Requires-Dist: ConfigArgParse
Requires-Dist: tqdm
Requires-Dist: PyYAML
Requires-Dist: ruamel.yaml
Requires-Dist: scipy
Project-URL: Home, https://github.com/hiemb/scan_image_slicer
Project-URL: Source, https://github.com/hiemb/scan_image_slicer
